hello_gunner/__init__.py
hello_gunner/cli.py
hello_gunner/py.typed
hello_gunner-0.1.2.dist-info/METADATA
hello_gunner-0.1.2.dist-info/WHEEL
hello_gunner-0.1.2.dist-info/entry_points.txt
hello_gunner-0.1.2.dist-info/top_level.txt
hello_gunner-0.1.2.dist-info/RECORD
